ecofreq/__init__.py
ecofreq/config.py
ecofreq/ecoctl.py
ecofreq/ecofreq.py
ecofreq/ecorun.py
ecofreq/ecostat.py
ecofreq/install.py
ecofreq/ipc.py
ecofreq/mqtt.py
ecofreq/utils.py
ecofreq/config/README.md
ecofreq/config/co2signal.cfg
ecofreq/config/default.cfg
ecofreq/config/docker.cfg
ecofreq/config/electricitymaps.cfg
ecofreq/config/energycharts.cfg
ecofreq/config/mock.cfg
ecofreq/config/mqtt.cfg
ecofreq/config/stromgedacht.cfg
ecofreq/config/ukgrid.cfg
ecofreq/config/watttime.cfg
ecofreq/data/co2trace.tsv
ecofreq/data/cpu_tdp.csv
ecofreq/helpers/__init__.py
ecofreq/helpers/amd.py
ecofreq/helpers/cgroup.py
ecofreq/helpers/cpu.py
ecofreq/helpers/docker.py
ecofreq/helpers/geo.py
ecofreq/helpers/ipmi.py
ecofreq/helpers/nvidia.py
ecofreq/helpers/suspend.py
ecofreq/installer/ecofreq.service
ecofreq/installer/install.sh
ecofreq/monitors/common.py
ecofreq/monitors/energy.py
ecofreq/monitors/freq.py
ecofreq/monitors/idle.py
ecofreq/monitors/manager.py
ecofreq/policy/common.py
ecofreq/policy/cpu.py
ecofreq/policy/governor.py
ecofreq/policy/gpu.py
ecofreq/policy/idle.py
ecofreq/policy/manager.py
ecofreq/providers/common.py
ecofreq/providers/manager.py
ecofreq/providers/mqtt.py
ecofreq/providers/rest.py
ecofreq-0.0.7.dist-info/METADATA
ecofreq-0.0.7.dist-info/WHEEL
ecofreq-0.0.7.dist-info/entry_points.txt
ecofreq-0.0.7.dist-info/licenses/LICENSE.txt
ecofreq-0.0.7.dist-info/RECORD
