Metadata-Version: 2.4
Name: ecofreq
Version: 0.0.7
Summary: EcoFreq: Dynamic carbon- and price-aware power scaling for CPUs and GPUs
Project-URL: Homepage, https://github.com/amkozlov/eco-freq
Project-URL: Issues, https://github.com/amkozlov/eco-freq/issues
Author-email: Oleksiy Kozlov <alexey.kozlov@h-its.org>
License-File: LICENSE.txt
Classifier: Development Status :: 3 - Alpha
Classifier: License :: Free for non-commercial use
Classifier: Operating System :: POSIX :: Linux
Classifier: Programming Language :: Python :: 3
Requires-Python: >=3.8
Requires-Dist: elevate
Requires-Dist: requests
Requires-Dist: typing-extensions
Provides-Extra: mqtt
Requires-Dist: aiomqtt; extra == 'mqtt'
